deconvolution/__init__.py
deconvolution/auxlib.py
deconvolution/exceptions.py
deconvolution/imageframe.py
deconvolution/pixeloperations.py
deconvolution-1.0.0.dist-info/DESCRIPTION.rst
deconvolution-1.0.0.dist-info/METADATA
deconvolution-1.0.0.dist-info/RECORD
deconvolution-1.0.0.dist-info/WHEEL
deconvolution-1.0.0.dist-info/metadata.json
deconvolution-1.0.0.dist-info/top_level.txt
