Metadata-Version: 2.0
Name: deconvolution
Version: 1.0.0
Summary: Package performing colour deconvolution
Home-page: https://github.com/grfrederic/deconvolution
Author: Frederic Grabowski, Pawel Czyz
Author-email: grabowski.frederic@gmail.com, pczyz@protonmail.com
License: BSD 3-Clause License
Platform: UNKNOWN
Requires-Dist: numpy
Requires-Dist: Pillow
